Metadata-Version: 2.4
Name: ciphers-vbcd-testing1
Version: 0.2.0
Summary: A tool for ciphering messages using various algorithms
Author-email: "Javier Novoa C." <jstitch@gmail.com>
Classifier: Programming Language :: Python :: 3
Classifier: License :: OSI Approved :: MIT License
Classifier: Operating System :: OS Independent
Requires-Python: >=3.9
Requires-Dist: click>=8.0.0
Provides-Extra: rsa
Requires-Dist: cryptography>=41.0.0; extra == "rsa"
Provides-Extra: build
Requires-Dist: build>=1.0.0; extra == "build"
Requires-Dist: wheel>=0.40.0; extra == "build"
Provides-Extra: deploy
Requires-Dist: twine>=4.0.0; extra == "deploy"
Provides-Extra: dev
Requires-Dist: pytest>=7.0.0; extra == "dev"
Requires-Dist: pytest-cov>=4.0.0; extra == "dev"
Requires-Dist: black>=23.0.0; extra == "dev"
Requires-Dist: isort>=5.12.0; extra == "dev"
Requires-Dist: ruff>=0.1.0; extra == "dev"
Requires-Dist: mypy>=1.0.0; extra == "dev"
